stellanow_sdk_python/__init__.py
stellanow_sdk_python/authentication/__init__.py
stellanow_sdk_python/authentication/auth_service.py
stellanow_sdk_python/authentication/exceptions.py
stellanow_sdk_python/config/__init__.py
stellanow_sdk_python/config/eniviroment_config/__init__.py
stellanow_sdk_python/config/eniviroment_config/stellanow_env_config.py
stellanow_sdk_python/config/enums/__init__.py
stellanow_sdk_python/config/enums/auth_strategy.py
stellanow_sdk_python/config/enums/logger_config.py
stellanow_sdk_python/config/read_env.py
stellanow_sdk_python/config/stellanow_auth_credentials.py
stellanow_sdk_python/config/stellanow_config.py
stellanow_sdk_python/configure_sdk.py
stellanow_sdk_python/message_queue/__init__.py
stellanow_sdk_python/message_queue/message_queue.py
stellanow_sdk_python/message_queue/message_queue_strategy/__init__.py
stellanow_sdk_python/message_queue/message_queue_strategy/base_deque_strategy.py
stellanow_sdk_python/message_queue/message_queue_strategy/fifo_message_queue_strategy.py
stellanow_sdk_python/message_queue/message_queue_strategy/i_message_queue_strategy.py
stellanow_sdk_python/message_queue/message_queue_strategy/lifo_message_queue_strategy.py
stellanow_sdk_python/message_queue/message_queue_strategy/overflow_strategy.py
stellanow_sdk_python/messages/__init__.py
stellanow_sdk_python/messages/base.py
stellanow_sdk_python/messages/event.py
stellanow_sdk_python/messages/message.py
stellanow_sdk_python/sdk.py
stellanow_sdk_python/sinks/__init__.py
stellanow_sdk_python/sinks/i_stellanow_sink.py
stellanow_sdk_python/sinks/mqtt/__init__.py
stellanow_sdk_python/sinks/mqtt/auth_strategy/__init__.py
stellanow_sdk_python/sinks/mqtt/auth_strategy/auth_factory.py
stellanow_sdk_python/sinks/mqtt/auth_strategy/i_mqtt_auth_strategy.py
stellanow_sdk_python/sinks/mqtt/auth_strategy/no_auth_mqtt_auth_strategy.py
stellanow_sdk_python/sinks/mqtt/auth_strategy/oidc_mqtt_auth_strategy.py
stellanow_sdk_python-0.1.5.dist-info/METADATA
stellanow_sdk_python-0.1.5.dist-info/WHEEL
stellanow_sdk_python-0.1.5.dist-info/RECORD
