Metadata-Version: 2.4
Name: stellanow-sdk-python
Version: 0.1.5
Summary: Welcome to the StellaNow Python SDK. This SDK is designed to provide an easy-to-use interface for developers integrating their Python applications with the StellaNow Platform. The SDK communicates with the StellaNow Platform using the MQTT.
License: This project is licensed under the terms of the MIT license.
Author: Stella Systems
Author-email: help@stella.systems
Requires-Python: >=3.11,<4.0
Classifier: License :: Other/Proprietary License
Classifier: Programming Language :: Python :: 3
Classifier: Programming Language :: Python :: 3.11
Classifier: Programming Language :: Python :: 3.12
Classifier: Programming Language :: Python :: 3.13
Classifier: Programming Language :: Python :: 3.14
Requires-Dist: loguru (>=0.7.2,<0.8.0)
Requires-Dist: nanoid (>=2.0.0,<3.0.0)
Requires-Dist: paho-mqtt (>=2.1.0,<3.0.0)
Requires-Dist: pydantic (>=2.10.6,<3.0.0)
Requires-Dist: stellanow-api-internals (>=0.0.5)
Requires-Dist: typing-extensions (>=4.10.0,<5.0.0)
